{
  "source": "https://tr.ibanvalidator.com/support/bank/5/akbank-ta.html",
  "updatedAt": "2026-05-14",
  "branches": {
    "1": "FİNANSAL MUHASEBE",
    "2": "ADANA",
    "3": "CEYHAN/ADANA",
    "4": "BAHÇEKAPI/ISTANBUL",
    "5": "ANKARA",
    "6": "İZMİR",
    "7": "KAYSERİ",
    "8": "DİYARBAKIR",
    "9": "KARŞIYAKA/.ARŞI/IZMIR",
    "10": "YENİGÜN/İZMİR",
    "11": "KIRIKKALE",
    "12": "DENİZLİ",
    "13": "BEŞİKTAŞ/ISTANBUL",
    "14": "POLATLI",
    "15": "YENİMAHALLE/ANKARA",
    "16": "SULTANHAMAM/ISTANBUL",
    "17": "CEBECİ/ANKARA",
    "18": "MERSİN",
    "19": "GALATA/İSTANBUL",
    "20": "KADIKÖY/ISTANBUL",
    "23": "KEMERALTI/IZMIR",
    "25": "ELAZIG",
    "26": "ESKİŞEHİR",
    "27": "ADAPAZARI",
    "28": "ATİKALİ/ISTANBUL",
    "29": "MALTEPE/KARTAL/İSTANBUL",
    "30": "ULUCANLAR/ANKARA",
    "31": "CANKIRI",
    "32": "BEYAZIT",
    "33": "KONYA",
    "34": "ŞANLIURFA",
    "35": "İSKENDERUN",
    "36": "BEYKOZ/ISTANBUL",
    "37": "EREGLİ/KONYA",
    "38": "SARIYER/ISTANBUL",
    "39": "BEYOGLU/İSTANBUL",
    "40": "AKŞEHİR/KONYA",
    "41": "ERZURUM",
    "42": "PANGALTI/ISTANBUL",
    "43": "BURSA",
    "44": "NAZİLLİ",
    "46": "Sabancı Center 4. Levent, İstanbul",
    "47": "EDREMİT",
    "48": "GEMLİK",
    "50": "UNKAPANI/ISTANBUL",
    "51": "SANAYI/KAYSERI",
    "52": "BASMAHANE/İZMİR",
    "53": "KARS",
    "54": "ŞİŞLİ/ISTANBUL",
    "55": "GAZİOSMANPAŞA/ISTANBUL",
    "56": "ANTALYA",
    "57": "GAZİANTEP",
    "58": "MAHMUTPAŞA/ISTANBUL",
    "59": "SAMSUN",
    "60": "MALATYA",
    "61": "KONAK/İZMİR",
    "62": "KARŞIYAKA/ADANA",
    "63": "SALIPAZARI/ISTANBUL",
    "64": "YENIŞEHIR/ANKARA",
    "65": "HASIRCILAR/ISTANBUL",
    "66": "İZMİT",
    "67": "TAKSIM/ISTANBUL",
    "68": "KASIMPAŞA/ISTANBUL",
    "69": "ÜSKÜDAR/ISTANBUL",
    "70": "SEBZEPAZARI/ADANA",
    "71": "SÖKE",
    "72": "SALİHLİ",
    "73": "BALIKESİR",
    "74": "TARSUS",
    "75": "NİŞANTAŞI/ISTANBUL",
    "76": "BÜYÜK KIRMIZI EV ZİNCİRLİKUYU ŞUBE",
    "77": "EREGLİ/KARADENİZ",
    "78": "BANDIRMA",
    "79": "TUZPAZARI/BURSA",
    "80": "SİRKECİ/ISTANBUL",
    "81": "KARABÜK",
    "82": "ANAFARTALAR/ANKARA",
    "83": "DÜZCE",
    "84": "NEVŞEHİR",
    "85": "SERİK/ANTALYA",
    "86": "SİVAS",
    "87": "MENEMEN",
    "88": "ANTAKYA",
    "89": "CORUM",
    "90": "PAZARYERİ /GAZİANTEP",
    "91": "ÖDEMİŞ",
    "93": "MANİSA",
    "94": "KEŞAN",
    "95": "AKHİSAR",
    "96": "BAHCELİEVLER/ANKARA",
    "97": "AYDIN",
    "99": "RİZE",
    "100": "TRABZON",
    "101": "KÜCÜKESAT/ANKARA",
    "102": "ALSANCAK/IZMIR",
    "103": "TOPTANCILAR CARŞISI/RAMİ",
    "104": "KÜCÜKSAAT/ADANA",
    "105": "ISPARTA",
    "106": "BERGAMA",
    "107": "BOLU",
    "108": "FETHİYE",
    "109": "İNÖNÜ BULVARI ŞUBESİ",
    "110": "KARŞIYAKA/SAHİL/IZMIR",
    "111": "GARAJLAR/BURSA",
    "112": "MALTEPE/ANKARA",
    "113": "HATAY/İZMİR",
    "114": "KÜTAHYA",
    "115": "UŞAK",
    "116": "KAVAKLIDERE/ANKARA",
    "117": "KAHRAMANMARAŞ",
    "118": "DARICA ŞUBESİ",
    "120": "EDİRNE",
    "121": "TEKİRDAG",
    "123": "BURDUR",
    "124": "CORLU/TEKIRDAG",
    "125": "LÜLEBURGAZ",
    "126": "UZUNKÖPRÜ",
    "127": "AFYONKARAHİSAR ŞUBESİ",
    "128": "MUGLA",
    "129": "KIRKLARELİ",
    "130": "CAYELİ/RIZE",
    "133": "MECİDİYEKÖY",
    "134": "KIZILTOPRAK/ISTANBUL",
    "135": "ŞAŞKINBAKKAL/İSTANBUL",
    "136": "BARTIN",
    "137": "ULUCAMİ/BURSA",
    "138": "ÇİFTEHAVUZLAR",
    "139": "SİNCAN/ANKARA",
    "140": "ÜMRANİYE/İSTANBUL",
    "141": "BAHARİYE/İSTANBUL",
    "142": "AKSARAY/İSTANBUL",
    "143": "FERİKÖY /İSTANBUL",
    "144": "TURGUTLU/MANİSA",
    "146": "ALTINOLUK ŞUBESİ",
    "147": "ERZİNCAN",
    "148": "ETİLER/İSTANBUL",
    "150": "BAKIRKÖY/İSTANBUL",
    "151": "AYDINLIKEVLER/ANKARA",
    "152": "FATİH/İSTANBUL",
    "153": "BAKANLIKLAR/ANKARA",
    "154": "AMASYA",
    "155": "KÖPRÜBAŞI /ESKİŞEHİR",
    "156": "BANKALAR CAD./İSTANBUL",
    "157": "YEŞİLYURT/İSTANBUL",
    "158": "GÜZELYALI/İZMİR",
    "159": "TİRE/İZMİR",
    "160": "TOKAT",
    "161": "KARTAL/ISTANBUL",
    "162": "PENDİK/İSTANBUL",
    "163": "KREDİ EKSPRES ALTIPARMAK ŞUBESİ",
    "164": "BORNOVA/İZMİR",
    "165": "EYÜP/İSTANBUL",
    "166": "HARBİYE",
    "167": "BEBEK/İSTANBUL",
    "168": "İNEGÖL/BURSA",
    "169": "ŞEHREMİNİ /İSTANBUL",
    "170": "KÜÇÜKYALI/ISTANBUL",
    "171": "GÜLTEPE/İSTANBUL",
    "172": "EMEK ŞUBESİ",
    "175": "LEVENT/İSTANBUL",
    "176": "KARAMAN",
    "177": "NURUOSMANİYE/İSTANBUL",
    "178": "CINNAH SB./ANKARA",
    "179": "MAMAK/ANKARA",
    "180": "NİGDE",
    "181": "İSTİNYE/İSTANBUL",
    "182": "BAHCELİEVLER/İSTANBUL",
    "183": "HAYRABOLU",
    "184": "DERİNCE/KOCAELİ",
    "185": "AKSARAY",
    "186": "ALİBEYKÖY/İSTANBUL",
    "187": "ORGANİZE SANAYİ/KAYSERİ",
    "188": "ŞİRİNEVLER/İSTANBUL",
    "189": "ZEYTİNBURNU/İSTANBUL",
    "190": "KASTAMONU",
    "191": "ALİAGA/İZMİR",
    "192": "SABANCI CENTER ŞUBESİ",
    "194": "KREDİ EKSPRES BÜYÜKÇEKMECE ŞUBESİ",
    "195": "BİGA",
    "196": "BAFRA/SAMSUN",
    "197": "BÜYÜKCEKMECE/İSTANBUL",
    "198": "CİHANGİR/İSTANBUL",
    "199": "KÜCÜKCEKMECE/İSTANBUL",
    "200": "KOCAMUSTAFAPAŞA/İSTANBUL",
    "203": "ZONGULDAK",
    "205": "GELİBOLU",
    "206": "BEKİRDERE/İZMİT",
    "207": "HASKÖY/İSTANBUL",
    "208": "TOPAGACI/İSTANBUL",
    "209": "CAMDİBİ/İZMİR",
    "210": "M.KEMALPAŞA/BURSA",
    "211": "CATALCA",
    "212": "SİLİVRİ",
    "213": "MERCAN/İSTANBUL",
    "214": "CANAKKALE",
    "215": "KIRŞEHİR",
    "216": "CEVİZLİ/İSTANBUL",
    "217": "ALTIPARMAK/BURSA",
    "218": "SAHRAYICEDİT /ISTANBUL",
    "219": "FOMARA ŞUBESİ",
    "220": "ORTAKÖY/İSTANBUL",
    "221": "ZAFER MEYDANI/KONYA",
    "224": "BURHANİYE",
    "225": "KARAMÜRSEL",
    "228": "PAZAR/RİZE",
    "229": "CARREFOURSA DİYARBAKIR ŞUBESİ",
    "230": "ORDU",
    "231": "İBRAHİMLİ ŞUBESİ",
    "232": "YALOVA",
    "233": "CİFTLİK CD./SAMSUN",
    "234": "ZİLE/TOKAT",
    "235": "HASANPAŞA/İSTANBUL",
    "237": "KUŞADASI",
    "238": "TUZLA/İSTANBUL",
    "239": "AKINCILAR/BALIKESİR",
    "240": "MERZİFON",
    "241": "NECATİBEY CAD/ANKARA",
    "242": "TEŞVİKİYE /İSTANBUL",
    "243": "GEBZE",
    "244": "MEVLANA/KONYA",
    "245": "DEVREK/ZONGULDAK",
    "246": "BOLVADİN/AFYON",
    "248": "BUCA/İZMİR",
    "249": "YÜZEVLER/ADANA",
    "250": "YEŞİLKÖY/İSTANBUL",
    "252": "HOPA",
    "253": "MİLAS",
    "254": "OF/TRABZON",
    "255": "CADDEBOSTAN/İSTANBUL",
    "256": "MODA/İSTANBUL",
    "257": "BAGLARBAŞI/İSTANBUL",
    "258": "OTO SANAYI/ISTANBUL",
    "260": "CEMALPAŞA/ADANA",
    "261": "BEYŞEHİR/KONYA",
    "262": "TARABYA/İSTANBUL",
    "263": "ATAKUM ŞUBESİ",
    "264": "FATSA/ORDU",
    "265": "VALİDECEŞME/İSTANBUL",
    "266": "BAYRAMPAŞA/İSTANBUL",
    "267": "BİGADİC/BALIKESİR",
    "271": "SOMA/MANİSA",
    "272": "REŞATBEY/ADANA",
    "273": "DEVELİ ŞUBESİ",
    "275": "YENİYOL/BURSA",
    "277": "AYAZPAŞA/İSTANBUL",
    "278": "LALAPAŞA/ERZURUM",
    "279": "BODRUM",
    "280": "METROPOL ŞUBESİ",
    "281": "İNCİRLİOVA ŞUBESİ",
    "282": "SUADİYE/İSTANBUL",
    "283": "NENEHATUN/ANKARA",
    "284": "HALİTZİYA/İZMİR",
    "286": "GİRESUN",
    "287": "GAYRETTEPE/İSTANBUL",
    "289": "AŞAGI AYRANCI/ANKARA",
    "290": "CARŞI/MERSİN",
    "291": "ÜCYOL/İZMİR",
    "292": "SEFAKÖY/İSTANBUL",
    "293": "SÜRMENE/TRABZON",
    "294": "GÖRELE/GİRESUN",
    "295": "İNCİRLİYOLU/İSTANBUL",
    "297": "KAZASKER",
    "298": "BARBAROS BULVARI/İSTANBUL",
    "299": "BOSTANLI/İZMİR",
    "303": "GARAJLAR/GAZİANTEP",
    "304": "KORDON/İZMİR",
    "305": "CANKAYA/ANKARA",
    "307": "GENCOSMAN/BURSA",
    "308": "AYVALIK",
    "309": "BEŞYOL/SEFAKÖY",
    "310": "KADİRLİ/OSMANİYE",
    "311": "KAZIMKARABEKIR SB.",
    "312": "CUBUK/ANKARA",
    "313": "ATATÜRK CADDESİ/ADANA",
    "314": "VAKFIKEBİR/TRABZON",
    "315": "GÖZTEPE/İSTANBUL",
    "317": "KOZAN/ADANA",
    "318": "ESKİ İSTASYON CAD/ADANA",
    "319": "EMİRDAG/AFYON",
    "321": "KIRKAGAC/MANİSA",
    "322": "İSTASYON CAD./ESKİŞEHİR",
    "323": "DEMETEVLER/ANKARA",
    "324": "CENNET MAH./İSTANBUL",
    "325": "SELİMİYE/İSTANBUL",
    "329": "YENİŞEHİR/BURSA",
    "331": "ŞARAMPOL/ANTALYA",
    "332": "DELİKLİCINAR/DENİZLİ",
    "333": "MANAVGAT/ANTALYA",
    "334": "SAYDAMCADDESİ/ADANA",
    "335": "GÖKSU ERYAMAN ŞUBESİ",
    "336": "YENİ ADANA",
    "338": "ARAKLI/TRABZON",
    "339": "ARNAVUTKÖY/İSTANBUL",
    "340": "ÜRGÜP/NEVSEHİR",
    "343": "KURTULUŞ ŞUBESİ",
    "345": "DİKMEN/ANKARA",
    "346": "ÜCKUYULAR/İZMİR",
    "347": "CUMHURİYET BULV/İZMİR",
    "348": "NARLIDERE/İZMİR",
    "349": "ARTVİN",
    "350": "BAYRAKLI/İZMİR",
    "351": "YAVUZLAR/ADANA",
    "352": "CAGLAYAN SB.IST.",
    "353": "CİNE/AYDIN",
    "354": "MİTHATPAŞA/ANKARA",
    "356": "KIZILAY/ANKARA",
    "357": "KAGITHANE/İSTANBUL",
    "358": "YOZGAT",
    "360": "RAHMANLAR ŞUBESİ",
    "362": "POZCU/MERSİN",
    "364": "CARŞAMBA/SAMSUN",
    "365": "AKCAABAT/TRABZON",
    "366": "BEYLERBEYİ/İSTANBUL",
    "367": "CENGELKÖY/İSTANBUL",
    "368": "MURATLI/TEKİRDAG",
    "370": "TAVŞANLI/KÜTAHYA",
    "371": "CAYCUMA/ZONGULDAK",
    "373": "GEDİZ/KÜTAHYA",
    "374": "EMNİYET CADDESİ/ŞANLIURFA ŞUBESİ",
    "375": "KECİÖREN/ANKARA",
    "376": "MALKARA/TEKİRDA.",
    "379": "AVANOS/NEVŞEHİR",
    "380": "YUKARI AYRANCI/ANKARA",
    "381": "KIRIKHAN/HATAY",
    "382": "NALCACI/KONYA",
    "383": "GÖZTEPE/İZMİR",
    "384": "KALEİCİ/DENİZLİ",
    "385": "KARŞIYAKA/GAZİANTEP",
    "386": "KESTEL ŞUBESİ",
    "387": "TİREBOLU/GİRESUN",
    "388": "DALYAN/İSTANBUL",
    "389": "KUYUBAŞI/İSTANBUL",
    "390": "OSMANBEY/İSTANBUL",
    "391": "GÜNGÖREN/İSTANBUL",
    "392": "KUMKAPI",
    "393": "ŞARKÖY/TEKİRDA.",
    "395": "TANDOGAN/ANKARA",
    "396": "NİSBETİYE/İSTANBUL",
    "399": "KOCAALİ/ADAPAZARI",
    "400": "NİZİP/GAZİANTEP",
    "401": "SİTELER/ANKARA",
    "402": "ETLİK/ANKARA",
    "403": "ANADOLUHİSARI/İSTANBUL",
    "404": "ATAKOY SB.IST.",
    "406": "SIRACEVİZLER/İSTANBUL",
    "407": "YENİKÖY/İSTANBUL",
    "408": "LIMAN /ALSANCAK",
    "409": "CIGLI/IZMIR",
    "410": "ŞEMİKLER/İZMİR",
    "411": "GAZİ BULVARI/İZMİR",
    "414": "BÜYÜKADA/İSTANBUL",
    "415": "GÜNGÖREN SANAYİ ŞUBESİ",
    "416": "YENİBOSNA/İSTANBUL",
    "417": "KANLICA/İSTANBUL",
    "418": "BAYBURT",
    "420": "ESENTEPE ŞUBESİ",
    "421": "SİİRT",
    "422": "MERTER/İSTANBUL",
    "423": "BATMAN",
    "425": "OSMANİYE",
    "426": "AVCILAR/İSTANBUL",
    "428": "ŞİRİNYER/İZMİR",
    "429": "ÜNYE/ORDU",
    "430": "DİNAR/AFYON",
    "431": "HÜRRİYET/BURSA",
    "432": "RUMELİ CAD./İSTANBUL",
    "433": "KONGRE/ERZURUM",
    "434": "AGRI",
    "435": "BAĞCILAR/İSTANBUL",
    "436": "ZİNCİRLİKUYU/İSTANBUL",
    "443": "YUSUFPAŞA/İSTANBUL",
    "444": "TOPCULAR/İSTANBUL",
    "445": "BULANCAK/GİRESUN",
    "446": "DÖRTYOL/HATAY",
    "447": "ESENLERKÖYÜ/İSTANBUL",
    "449": "TOPKAPI SANAYİ/İSTANBUL",
    "451": "SORGUN ŞUBESİ",
    "452": "BALCOVA/İZMİR",
    "453": "ALAŞEHİR/MANİSA",
    "456": "VAN",
    "457": "REYHANLI/HATAY",
    "458": "ALANYA/ANTALYA",
    "459": "KREDİ EKSPRES KAYNARCA ŞUBESİ",
    "461": "GÖNEN/BALIKESİR",
    "462": "SOĞANLIK ŞUBESİ",
    "463": "TORBALI/İZMİR",
    "464": "BUHARA BULVARI ŞUBESİ",
    "465": "SUSURLUK/BALIKESİR",
    "466": "MARDİN",
    "467": "GAZIPAŞA/ANTALYA ŞUBESİ",
    "468": "KULU/KONYA",
    "469": "CİVRİL/DENİZLİ",
    "472": "SİVEREK/ŞANLIURFA",
    "473": "ARDEŞEN/RİZE",
    "476": "URLA/IZMIR ŞUBESİ",
    "478": "KARACABEY/BURSA",
    "481": "TAVAS/DENİZLİ",
    "482": "BEYPAZARI/ANKARA",
    "483": "GAZİEMİR/ULAŞTIRMA ŞUBESİ",
    "484": "ILGIN/KONYA",
    "485": "BABAESKİ/KIRKLARELİ",
    "487": "KREDİ EKSPRES KIZILAY ŞUBESİ",
    "488": "BUCAK/BURDUR",
    "489": "FOÇA ÇIKARMA FİLOSU ŞUBESİ",
    "490": "ORHANGAZİ/BURSA",
    "492": "SİLİFKE/İ.EL",
    "493": "BİLECİK TUGAY ŞUBESİ",
    "494": "İÇMELER ŞUBESİ",
    "495": "ELMADAG/ANKARA",
    "496": "KREDİ EKSPRES PENDİK ŞUBESİ",
    "497": "IĞDIR/KARS",
    "498": "MUŞ",
    "499": "ADIYAMAN",
    "500": "SINDIRGI/BALIKESİR",
    "502": "SİMAV/KÜTAHYA",
    "504": "ANAMUR/MERSİN",
    "506": "SEFERİHİSAR/İZMİR",
    "507": "TURHAL/TOKAT",
    "509": "KÜCÜKKÖY/İSTANBUL",
    "512": "KAYSERİ PARK ŞUBESİ",
    "514": "AYANCIK/SİNOP",
    "515": "NİKSAR/TOKAT",
    "516": "TAŞKÖPRÜ/KASTAMONU",
    "517": "ESPİYE/GİRESUN",
    "518": "SARAY/TEKİRDAG",
    "520": "KORKUTELİ/ANTALYA",
    "521": "ERENLER ŞUBESİ",
    "522": "KUMLUCA/ANTALYA",
    "524": "İPSALA/EDİRNE",
    "525": "PAMUKOVA/ADAPAZARI",
    "526": "CAN/CANAKKALE",
    "528": "ARHAVİ/ARTVİN",
    "529": "BİLECİK",
    "531": "ARDAHAN",
    "532": "ERBAA/TOKAT",
    "533": "PAC MEYDANI/İSKENDERUN",
    "534": "VİZE/KIRKLARELİ",
    "536": "BİNGÖL",
    "537": "ORTACA/MUGLA",
    "538": "ABİDİNPAŞA/ANKARA",
    "540": "KREDİ EKSPRES AVCILAR ŞUBESİ",
    "541": "KIZILTEPE/MARDİN",
    "542": "SELCUK/İZMİR",
    "543": "KULA/MANİSA",
    "544": "KALABA/ANKARA",
    "546": "İMES SANAYİ ŞUBESİ",
    "547": "SARUHANLI/MANİSA",
    "548": "OSMANCIK/CORUM",
    "549": "KÖRFEZ/KOCAELİ ŞUBESİ",
    "550": "KORUPARK ŞUBESİ",
    "551": "SANAYİ SİTESİ BALIKESİR",
    "552": "SANDIKLI/AFYON",
    "553": "SAN.SİT./SAMSUN",
    "554": "SULUOVA/AMASYA",
    "556": "BOZUYUK/BILECIK",
    "557": "AKYAZI/ADAPAZARI",
    "558": "SULTANÇIFTLIĞI ŞUBESİ",
    "560": "EFELER ŞUBESİ AYDIN",
    "562": "MUDANYA/BURSA",
    "563": "CERKEZKÖY/TEKİRDA.",
    "564": "BOYABAT/SİNOP",
    "566": "DİVRİGİ/SİVAS",
    "567": "ETİMESGUT/ANKARA",
    "568": "OFİS/DİYARBAKIR",
    "569": "KARA KUVVETLERİ KOMUTANLIĞI",
    "570": "ICERENKOY SB./İSTANBUL",
    "571": "ÜMRANİYE SANAYİ ŞUBESİ",
    "572": "KAYNARCA/İSTANBUL",
    "573": "KEMALPAŞA/İZMİR",
    "574": "YILDIRIM /BURSA",
    "575": "EZİNE/CANAKKALE",
    "576": "TSK REHABİLİTASYON ŞUBESİ",
    "577": "AKDENİZ SANAYİ SİTESİ ŞUBESİ",
    "578": "BİRLİK ŞUBESİ/ANKARA",
    "580": "ELBİSTAN ŞUBESİ/KAHRAMANMARAŞ",
    "581": "KARA HAVACILIK KOMUTANLIĞI ŞUBESİ",
    "584": "SARIGAZİ ŞUBESİ",
    "585": "BAYRAK ŞUBESİ",
    "587": "İMAMOGLU/ADANA",
    "588": "ÇELİKTEPE ŞUBESİ",
    "589": "İKİTELLİ ORGANİZE SANAYİ ŞUBESİ",
    "590": "ERDEMLİ/MERSİN",
    "591": "DEGİRMENDERE/TRABZON",
    "593": "ARGINCIK/KAYSERİ",
    "596": "SEYRANTEPE ŞUBESİ",
    "597": "GİRNE BULVARI ŞUBESİ",
    "599": "YATAGAN/MUGLA",
    "601": "KAYNARCA/ADAPAZARI",
    "602": "İNEBOLU/KASTAMONU",
    "603": "OSTİM SANAYİ SİTESİ/ANKARA",
    "605": "CEKİRGE/BURSA",
    "606": "OSMANİYE/İSTANBUL",
    "607": "AKATLAR/İSTANBUL",
    "609": "AKDENİZ BULVARI/ANTALYA",
    "610": "ERDEK/BALIKESİR",
    "611": "FEVZİ CAKMAK/KAYSERİ",
    "612": "BARKAL ŞUBESİ",
    "613": "KARABAGLAR/İZMİR",
    "615": "MARMARİS/MUGLA",
    "616": "YENİ GIDA CRŞ./İZMİR",
    "617": "3.SANAYI SITESI/IZMIR",
    "618": "EĞİTİM VE DOKTRİN KOMUTANLIĞI ŞB",
    "619": "LİKYA ŞUBESİ",
    "620": "YAYLADURAGI/İSTANBUL",
    "621": "BUGDAYPAZARI/SAMSUN",
    "622": "MERSİN SERBEST BÖLGE ŞUBESİ",
    "623": "İSTİKLAL CAD./ANTAKYA",
    "624": "GAZİPAŞA BULV./ADANA",
    "625": "KENTSA",
    "626": "BARAJYOLU SB.ADANA",
    "627": "YENI TOPTANCI HALI/ADANA",
    "628": "IMES ŞUBESİ",
    "630": "KERESTECILER SITESI",
    "631": "GIMAT",
    "632": "KOZYATAGI SB.",
    "633": "PERPA/ISTANBUL",
    "634": "ATATURK ORGANIZE SAN.BOL./IZMIR",
    "635": "GUNESLI/ISTANBUL",
    "636": "ULUS SB.",
    "638": "SULTANBEYLI SB.",
    "640": "ISTOC SB.",
    "641": "KURTKOY SB.",
    "642": "DEGIRMICEM SB.",
    "643": "BESYUZEVLER SB.",
    "644": "BEYLIKDUZU /ISTANBUL",
    "645": "MASLAK SB.",
    "646": "BALGAT SB.",
    "647": "GAZIEMIR SB.",
    "648": "HACI SABANCI ORG.SAN.BOL./ADANA",
    "651": "GUMBET",
    "652": "ATAKÖY 5. KISIM",
    "653": "KEMER",
    "654": "CESME",
    "656": "ODTU",
    "658": "YILDIZ ŞUBESİ",
    "659": "KENAN EVREN SITESI",
    "661": "ERYAMAN",
    "662": "GATEM",
    "663": "GAZİOSMANPAŞA/ANKARA",
    "665": "CARREFOURSA/ADANA",
    "666": "CARREFOURSA-UMRANIYE/ISTANBUL",
    "667": "BILKENT",
    "668": "PROFILO",
    "670": "CUKUROVA UNIVERSITESI",
    "674": "YENIHAL/MERSIN",
    "678": "4.SANAYI SITESI",
    "680": "YEŞİLYAYLA ŞUBESİ",
    "681": "AKINCI",
    "683": "BAHABEY CADDESİ",
    "685": "FOCA/IZMIR",
    "689": "ALKENT",
    "690": "FLORYA",
    "692": "ORTAKLAR CADDESİ",
    "693": "SANAYI/IZMIT",
    "694": "EMLAK KONUT",
    "695": "ÜST BOSTANCI",
    "696": "2.SITELER",
    "698": "YESILPINAR",
    "699": "DENİZLİ SANAYİ ŞUBESİ",
    "700": "ÇİĞLİ 2.ANA JET ÜSSÜ ŞUBESİ",
    "704": "DOĞUBEYAZIT",
    "705": "ESKIŞEHIR SANAYI ŞUBESİ",
    "706": "KIŞLA CADDESİ/TOPÇULAR ŞUBESİ",
    "708": "YENISANAYI/KAYSERI",
    "709": "TOROS SB./ADANA",
    "710": "DEMIRCILER SITESI/IST",
    "711": "TOPTANCILAR SİTESİ/SİVAS",
    "712": "ANTARES ŞUBESİ /ANKARA",
    "713": "SABANCI UNIVERSITESI",
    "714": "LARA",
    "715": "KUCUKBAKKALKOY/IST",
    "716": "PINARBASI/IZMIR",
    "717": "MTK CARSISI",
    "718": "CARREFOURSA/IZMIT",
    "719": "VIRANŞEHIR ŞUBESİ/ŞANLIURFA",
    "720": "SİLOPİ",
    "721": "CARREFOURSA-KOZYATAGI/ISTANBUL",
    "726": "ATATURK HAVALIMANI SB.",
    "727": "BATIKENT",
    "728": "SULTANBEYLİ TEM ŞUBESİ",
    "729": "CAYIROVA/KOCAELI",
    "730": "GOLBASI/ANKARA",
    "731": "BOĞAZİÇİ ÜNİVERSİTESİ",
    "732": "TANJANT YOLU/TRABZON",
    "733": "CARREFOURSA / IZMIR",
    "736": "ACIBADEM SB.",
    "737": "MUMHANEONU SB.",
    "738": "ISIKKENT SB./IZMIR",
    "739": "CEPA ŞUBESİ/ANKARA",
    "741": "OZEL BANKACILIK ETİLER MERKEZ ŞUBE",
    "742": "KREDİ EKSPRES ALSANCAK ÇARŞI ŞUBESİ",
    "744": "ÜMİTKÖY ŞUBESİ",
    "745": "CARREFOURSA İSTİNYE",
    "746": "ÖZKANLAR/BORNOVA",
    "747": "MEZITLI ŞUBESİ",
    "749": "CARREFOURSA BURSA",
    "750": "CARREFOURSA HARAMIDERE/IST.",
    "751": "CEVAHİR",
    "752": "OZEL BANKACILIK ANKARA",
    "753": "OZEL BANKACILIK SUADIYE",
    "754": "ADATEPE ŞUBESİ",
    "760": "CARREFOURSA ANKARA",
    "762": "ESENYURT ŞUBESİ",
    "763": "ISTANBUL KURUMSAL SB.",
    "764": "GEZICI SUBE OZGUR1",
    "765": "SABANCI CENTER(GEZICI ŞUBE-ÖZGÜR 2)",
    "766": "BOSTANCI DORTYOL/ISTANBUL",
    "767": "ATASEHIR/ISTANBUL",
    "768": "AKMERKEZ/ISTANBUL",
    "771": "ATRIUM/ISTANBUL",
    "772": "OZEL BANKACILIK IZMIR SB.",
    "773": "SELÇUKLU SANAYİ ŞUBESİ",
    "775": "OZEL BANKACILIK NISANTASI",
    "776": "BOR SB.",
    "781": "SISLI TICARI SB.",
    "782": "ÖZEL BANKACILIK ADANA ŞUBESİ",
    "784": "ÖZEL BANKACILIK BURSA ŞUBESİ",
    "785": "IKITELLI",
    "786": "MASLAK TICARI SUBE",
    "787": "BATI KURUMSAL SB.",
    "788": "GUNESLI TICARI ŞUBESİ",
    "789": "GAYRETTEPE TICARI SB.",
    "791": "IHLAMURKUYU ŞUBESİ",
    "792": "BAŞAKŞEHİR",
    "794": "BAHÇEŞEHIR",
    "795": "CAPITOL ŞUBESİ",
    "796": "CARREFOURSA MERSIN",
    "797": "SAYISTAY SB./ANK",
    "798": "DOĞU KURUMSAL",
    "799": "KOZYATAĞI TICARI",
    "800": "FORUM/BORNOVA ŞUBESİ",
    "802": "KREDİ EKSPRES ZEYTİNBURNU ŞUBESİ",
    "803": "KALKAN ŞUBESİ",
    "804": "KONYAALTI ŞUBESİ",
    "806": "TERME ŞUBESİ",
    "807": "100. YIL/ANTALYA",
    "809": "ÇEKMEKÖY",
    "810": "GAZİEMİR HAVA TEKNİK OKULLARI ŞB",
    "811": "YALOVAYOLU ŞUBESİ",
    "812": "BELEK",
    "813": "DAVUTPAŞA ŞUBESİ",
    "814": "KAPAKLI ŞUBESİ",
    "815": "DAMLATAŞ ŞUBESİ",
    "817": "BEYLİKDÜZÜ SANAYİ ŞUBESİ",
    "819": "NARLIDERE İSTİHKAM OKULU ŞUBESİ",
    "821": "SABİHA GÖKÇEN HAVAALANI",
    "822": "FULYA ŞUBESİ",
    "823": "GÜNEY DENİZ SAHA KOMUTANLIĞI ŞUBESİ",
    "824": "LİMAN/MERSİN",
    "826": "ANKARA ADLİYESİ",
    "827": "İZMİR ADLİYESİ",
    "829": "CARREFOURSA BAYRAMPAŞA",
    "830": "CARREFOURSA BAĞCILAR ŞUBESİ",
    "831": "TOYOTA ŞUBESİ",
    "832": "BAŞKENT KURUMSAL",
    "833": "ADANA TICARI",
    "834": "ANKARA TICARI",
    "835": "BAHÇEKAPI TICARI",
    "836": "IZMIR TICARI",
    "838": "BURSA TICARI",
    "839": "GALATA TICARI",
    "841": "GEBZE TICARI",
    "843": "KAYSERI TICARI",
    "844": "ASPENDOS BULVARI",
    "845": "ÇUKUROVA KURUMSAL",
    "848": "EGE KURUMSAL",
    "849": "ANTALYA TİCARİ",
    "864": "ÇANKAYA TİCARİ",
    "865": "DENİZLİ TİCARI",
    "866": "ALTUNİZADE",
    "867": "IKITELLI TICARI",
    "868": "PENDİK TİCARİ",
    "870": "AVCILARE5",
    "874": "ULUYOL CADDESI",
    "875": "GAZİANTEP TİCARİ",
    "876": "IMES TICARI",
    "881": "GEBZE E5",
    "882": "GÖKTÜRK",
    "883": "MERTER TICARI",
    "884": "HADIMKÖY",
    "885": "ATATÜRK BULVARI /ADAPAZARI",
    "886": "MAHFESIĞMAZ ŞUBESİ",
    "887": "NİLÜFER ŞUBESİ",
    "889": "PENDİK E5",
    "891": "SİNOP",
    "892": "IŞIKLAR ŞUBESİ",
    "894": "CARREFOURSA MALTEPE",
    "895": "TRAKYA ÜNİVERSİTESİ",
    "896": "KONYA TICARI",
    "900": "ISTANBUL MERKEZI VEZNE MÜDÜRLÜĞÜ",
    "905": "KOZYATAĞI N.O.M",
    "907": "TAKAS ISTANBUL ŞEHİR",
    "908": "İKİTELLİ N.O.M",
    "909": "SEHIR TAKASI ISTANBUL",
    "917": "SELÇUK ÜNİVERSİTESİ",
    "922": "BÜSAN SANAYİ",
    "926": "SIDE",
    "932": "GAZİ ÜNİVERSİTESİ",
    "940": "EGE ÜNİVERSİTESİ ŞUBESİ",
    "942": "DALAMAN ŞUBESİ",
    "944": "HALİKARNAS",
    "945": "İVEDİK",
    "947": "ÇALLI ŞUBESİ",
    "951": "KREDI KARTLARI MERKEZI",
    "954": "DİDİM",
    "955": "KREDİ EKSPRES GEBZE",
    "956": "MERSİN ÜNİVERSİTESİ",
    "964": "KAVACIK",
    "966": "TOSYA ŞUBESİ",
    "967": "ÇEK OPERASYON MERKEZI SUBESI",
    "968": "YENİMAHALLE/ORDU",
    "988": "GÖLCÜK",
    "989": "GAZCILAR ŞUBESİ",
    "990": "1. SANAYİ SİTESİ/İZMİR",
    "991": "MİMAR SİNAN",
    "993": "KADİR HAS ÜNİVERSİTESİ",
    "994": "MEGACENTER ŞUBESİ",
    "995": "BEŞEVLER SANAYİ",
    "999": "DIS ISLEMLER GRUBU",
    "1002": "CITYS NİŞANTAŞI ŞUBESİ",
    "1003": "EGE ORDU KOMUTANLIĞI ŞUBESİ",
    "1004": "12.HAVA ULAŞTIRMA ANA ÜS KOMUTANLIĞI",
    "1005": "2.HAVA İKMAL BAKIM MERKEZ KOMUTANLIĞI",
    "1006": "KARA KUVVETLERİ LOJİSTİK KOMUTANLIĞI",
    "1007": "5.ANA BAKIM MERKEZİ ŞUBESİ",
    "1008": "İSKENDERUN 39.MEKANİZE ŞUBESİ",
    "1009": "İSKENDERUN DENİZ ALAYI ŞUBESİ",
    "1010": "8.KOLORDU KOMUTANLIĞI ŞUBESİ",
    "1011": "2.HAVA KUVVETLERİ KOMUTANLIĞI ŞUBE",
    "1012": "KÜTAHYA HAVA TUGAYI ŞUBESİ",
    "1013": "KOCASİNAN ŞUBESİ",
    "1014": "GÖCEK ŞUBESİ",
    "1015": "KREDİ EKSPRES ÇİĞLİ ŞUBESİ",
    "1016": "MALATYA 2.ORDU KOMUTANLIĞI ŞUBESİ",
    "1017": "EĞİRDİR DAĞ KOMANDO OKULU ŞUBESİ",
    "1018": "KARAMÜRSELBEY EĞİTİM MERKEZ KOMUTANLIĞI",
    "1019": "3. KOLORDU KOMUTANLIĞI ŞUBESİ",
    "1020": "ÇEVREYOLU/MANİSA ŞUBESİ",
    "1021": "İSLAHİYE/GAZİANTEP ŞUBESİ",
    "1022": "GÖLCÜK DONANMA ŞUBESİ",
    "1023": "YALVAÇ ŞUBESİ",
    "1024": "BATI ATAŞEHİR ŞUBESİ",
    "1025": "ELMALI ŞUBESİ",
    "1028": "KREDİ EKSPRES SAMSUN ŞUBESİ",
    "1030": "KREDİ EKSPRES POZCU ŞUBESİ",
    "1031": "BİNEVLER ŞUBESİ",
    "1032": "ÇARŞI/GAZİANTEP",
    "1034": "KREDİ EKSPRES DENİZLİ",
    "1035": "FİNİKE ŞUBESİ",
    "1036": "KEPEZ ŞUBESİ",
    "1037": "KARASU ŞUBESİ",
    "1041": "KREDİ EKSPRES KARTAL ŞUBESİ",
    "1042": "İZNİK ŞUBESİ",
    "1044": "KREDİ EKSPRES ÇERKEZKÖY ŞUBESİ",
    "1045": "AKSE SAPAĞI ŞUBESİ GEBZE",
    "1046": "KREDİ EKSPRES ORDU ŞUBESİ",
    "1047": "BÜLENT ECEVİT BULVARI ŞUBESİ",
    "1048": "ESENKENT ŞUBESİ",
    "1050": "KENAN EVREN KIŞLASI ŞUBESİ",
    "1051": "MUHABERE ELEKTRONİK BİLGİ SİS.OKULU",
    "1052": "BOLU 2.KOMANDO TUGAYI ŞUBESİ",
    "1053": "KREDİ EKSPRES BALÇOVA ŞUBESİ",
    "1054": "LİBADİYE ŞUBESİ",
    "1055": "SAĞLIK MAHALLESİ ŞUBESİ",
    "1056": "ALAADDİN/KONYA ŞUBESİ",
    "1057": "GİRNE BULVARI(KE B.ÇİĞLİ KİPA)BAĞLI",
    "1058": "YILDIZ(KE BOYNER PANORA)BAĞLI ŞUBE",
    "1075": "TOROSLAR ŞUBESİ",
    "1076": "SANAYİ İNEGÖL ŞUBESİ",
    "1078": "PALLADİUM AVM ŞUBESİ",
    "1079": "YALIKAVAK ŞUBESİ",
    "1080": "KIZILCAHAMAM ŞUBESİ",
    "1081": "SAKARYA CADDESİ ŞUBESİ",
    "1082": "ELVANKENT ŞUBESİ",
    "1083": "OKMEYDANI ŞUBESİ",
    "1084": "GAZİ MAHALLESİ ŞUBESİ",
    "1090": "KREDİ EKSPRES ÇORLU ŞUBESİ",
    "1091": "MEYDAN/ANTALYA ŞUBESİ",
    "1093": "ALEMDAR ŞUBESİ",
    "1094": "KAZAN ŞUBESİ",
    "1095": "DİKİLİ ŞUBESİ",
    "1096": "ZAFER CADDESİ/KIRIKKALE ŞUBESİ",
    "1097": "SAMSUN ORGANİZE SANAYİ ŞUBESİ",
    "1098": "BOLU SANAYİ ŞUBESİ",
    "1100": "ATATÜRK BULVARI/ESKİŞEHİR ŞUBESİ",
    "1102": "KREDİ EKSPRES EDİRNE ŞUBESİ",
    "1104": "MANİSA 1 PİYADE EĞİTİM TUGAY KOM.ŞB",
    "1105": "1.MEKANİZE PİYADE TUGAY KOM.ŞB",
    "1106": "ARNAVUTKÖY/GAZİOSMANPAŞA ŞUBESİ",
    "1107": "KASTAMONU SANAYİ ŞUBESİ",
    "1108": "SANAYİ/TOKAT ŞUBESİ",
    "1109": "FIRAT ŞUBESİ",
    "1110": "ALAÇATI ŞUBESİ",
    "1112": "HALKALI ŞUBESİ",
    "1114": "SANAYİ/BANDIRMA ŞUBESİ",
    "1119": "ÖZEL BANKACILIK BATI ISTANBUL ŞUBES",
    "1123": "PLAZA KURUMSAL ŞUBESİ",
    "1124": "NEO PENDİK ŞUBESİ",
    "1129": "KREDİ EKSP.CARREFOUR-SA BAYRAMPAŞA",
    "1130": "KREDİ EKSP.CARREFOUR-SA HARAMİDERE",
    "1131": "KREDİ EKSPRES CARREFOUR-SA ŞUBESİ",
    "1152": "KREDİ EKSPRES CARREFOUR-SA PENDİK",
    "1153": "ÖZEL BANKACILIK KOZYATAĞI ŞUBESİ",
    "1157": "KREDİ EKSPRES CARREFOURSA ERZURUM",
    "1159": "ÜMRANIYE(KE İKEA ÜMRANİYE)BAĞLI ŞB",
    "1160": "YALOVAYOLU(KE İKEA BURSA)BAĞLI ŞUBE",
    "1161": "FORUM/BORNOVA(KE İKEA BORNOVA)BAĞLI",
    "1162": "ULUYOL CADDESI (KE İKEABAYRAMPAŞA",
    "1167": "SANAYİ/ÇORUM ŞUBESİ",
    "1168": "STARCİTY ŞUBESİ",
    "1169": "KİLİS ŞUBESİ",
    "1170": "GÜRSU ŞUBESİ",
    "1171": "SEYDİŞEHİR ŞUBESİ",
    "1172": "ERDEMİR CADDESİ ŞUBESİ",
    "1173": "SİVAS CADDESİ/KAYSERİ ŞUBESİ",
    "1174": "MASKO ŞUBESİ",
    "1175": "RADAR/YENİBOSNA ŞUBESİ",
    "1176": "YÜZYIL MAHALLESİ ŞUBESİ",
    "1177": "ZEKERİYAKÖY ŞUBESİ",
    "1179": "ERTUĞRULKENT ŞUBESİ",
    "1180": "AKÇAY ŞUBESİ",
    "1184": "ABM ŞUBESİ",
    "1186": "KAYAPINAR ŞUBESİ",
    "1187": "ÇUKURAMBAR ŞUBESİ",
    "1188": "ERTUĞRULGAZİ ŞUBESİ",
    "1189": "KOĞUKÇINAR ŞUBESİ",
    "1190": "ŞAŞMAZ ŞUBESİ",
    "1191": "FİKİRTEPE ŞUBESİ",
    "1192": "FİRUZKÖY ŞUBESİ",
    "1193": "GÜLBAHAR CADDESİ ŞUBESİ",
    "1194": "SOĞANLI ŞUBESİ",
    "1196": "İZMİRYOLU/BURSA ŞUBESİ",
    "1197": "KARATAY SANAYİ ŞUBESİ",
    "1198": "TAVUKÇUYOLU ŞUBESİ",
    "1199": "ÇARŞI/BALIKESİR ŞUBESİ",
    "1200": "LALELİ ŞUBESİ",
    "1201": "ORGANİZE SANAYİ/G.ANTEP ŞUBESİ",
    "1202": "KOŞUYOLU ŞUBESİ",
    "1203": "DES ŞUBESİ",
    "1204": "SULTANGAZİ ŞUBESİ",
    "1205": "UNCALI ŞUBESİ",
    "1206": "VİŞNE CADDESİ ŞUBESİ",
    "1207": "TATVAN ŞUBESİ",
    "1208": "TERAZİDERE ŞUBESİ",
    "1209": "İBRAHİMAĞA CADDESI ŞUBESİ",
    "1210": "AMBAR YOLU ŞUBESİ",
    "1211": "ERİKLİ ŞUBESİ",
    "1212": "DUDULLU ŞUBESİ",
    "1214": "TONGUÇ CADDESİ ŞUBESİ",
    "1215": "ALACAATLI KAVŞAĞI ŞUBESİ",
    "1216": "DUMLUPINAR ŞUBESİ",
    "1217": "KELKİT ŞUBESİ",
    "1218": "BURHANETTİN ONAT ŞUBESİ",
    "1219": "İSTANBUL CADDESİ ŞUBESİ",
    "1222": "SAMANDIRA ŞUBESİ",
    "1223": "GÜMÜŞHANE ŞUBESİ",
    "1224": "BUCA MEYDAN ŞUBESİ",
    "1225": "KARATAŞ ŞUBESİ",
    "1226": "TEKSTİLKENT ŞUBESİ",
    "1227": "HENDEK ŞUBESİ",
    "1228": "FENER CADDESİ ŞUBESİ",
    "1229": "MERDİVENKÖY ŞUBESİ",
    "1230": "SANAYİ/ANTAKYA ŞUBESİ",
    "1231": "ASYA KURUMSAL ŞUBE",
    "1232": "RUMELİ KURUMSAL ŞUBE",
    "1233": "4.LEVENT ŞUBESİ",
    "1234": "PORTFÖY SAKLAMA ŞUBESİ",
    "1235": "TUZLA ORGANİZE SANAYİ ŞUBESİ",
    "1236": "YILDIZTABYA ŞUBESİ",
    "1237": "DOSAB BURSA ŞUBESİ",
    "1238": "GÜLKENT ŞUBESİ",
    "1239": "İNÖNÜ MAHALLESİ ŞUBESİ",
    "1241": "ÖRNEK MAHALLESİ ŞUBESİ",
    "1242": "TAŞDELEN ŞUBESİ",
    "1245": "ANKARA OSB ŞUBESİ",
    "1246": "ZEYTINBURNU BULVAR ŞUBESİ",
    "1247": "YENİ GİRNE ŞUBESİ",
    "1248": "ALTINTEPE ŞUBESİ",
    "1249": "CUMHURİYET CADDESİ ŞUBESİ",
    "1250": "YAŞAMKENT ŞUBESİ",
    "1251": "DİLOVASI ŞUBESİ",
    "1252": "NATO YOLU/ÇENGELKÖY ŞUBESİ",
    "1253": "ETHEMEFENDİ ŞUBESİ",
    "1254": "ÇEVREYOLU/UŞAK ŞUBESİ",
    "1255": "KAVACIK(ACR LOFT)BAĞLI ŞUBESİ",
    "1256": "BİNEVLER ŞUBESİ",
    "1257": "SERDİVAN ŞUBESİ",
    "1259": "ŞAHİNBEY CADDESİ ŞUBESİ",
    "1260": "İZMİT E5 ŞUBESİ",
    "1261": "TORİUM ŞUBESİ",
    "1262": "FERHATPAŞA ŞUBESİ",
    "1265": "KUŞADASI (KUŞADASI/ÇARŞI) BAĞLI",
    "1266": "DAVUTLAR",
    "1268": "ESKİŞEHİR OSB ŞUBESİ",
    "1273": "VADİSTANBUL",
    "1275": "YILDIZTEPE ŞUBESİ",
    "1277": "TUZLA İÇMELER ŞUBESİ",
    "1278": "ALANYA SANAYİ ŞUBESİ",
    "1282": "GAZIEMIR ÇARŞI ŞUBESI",
    "1283": "YENI TOPTANCILAR SITESI ŞUBESI",
    "1284": "KAYIŞDAĞI CADDESI ŞUBESI",
    "1285": "KARTAL NOM",
    "1300": "TURGUTREİS ŞUBESİ",
    "1308": "GÜZELYALI ŞUBESİ",
    "1320": "BEYKENT ŞUBESİ",
    "1321": "UZUNYALI ŞUBESİ",
    "1325": "İVEDİK ORGANİZE SANAYİ ŞUBESİ",
    "1328": "KARAKÖPRÜ/ŞANLIURFA ŞUBESİ",
    "1330": "KONAKLI ŞUBESİ",
    "1334": "DOĞA CADDE/MALATYA ŞUBESİ",
    "1337": "MANAVGAT SANAYI ŞUBESI",
    "1339": "DEMOKRASİ MEYDANI ŞUBESİ",
    "1340": "GÜLBAĞ ŞUBESI",
    "1341": "BOSTANCI OTO SANAYİ ŞUBESİ",
    "1342": "MAHMUTLAR ŞUBESİ",
    "1343": "ESENYURT ÇARŞI ŞUBESİ",
    "1344": "ÜMRANİYE SANTRAL ŞUBESİ",
    "1346": "GÜZELLER OSB ŞUBESİ",
    "1349": "SEYİTNİZAM/ZEYTİNBURNU ŞUBESİ",
    "1356": "ERENKÖY ŞUBESI",
    "1359": "MEVLANA KAVŞAĞI ŞUBESI",
    "1360": "DİCLEKENT BULVARI ŞUBESİ",
    "1362": "ACARKENT ŞUBESI",
    "1372": "DİCLE ŞUBESİ",
    "1376": "İKİTELLİ ORGANİZE SANAYİ ŞUBESİ",
    "1377": "İPEKYOLU/VAN ŞUBESİ",
    "1379": "MALTEPE E-5 ŞUBESİ",
    "1386": "GMK BULVARI ŞUBESİ",
    "1389": "ATAKUM(19 MAYIS ÜNİVERSİTESİ)BAĞLI",
    "1392": "TÜRKMENBAŞI",
    "1394": "ZORLU CENTER ŞUBESİ",
    "1396": "RAMAN",
    "1401": "DÖŞEMEALTI",
    "1406": "ÇEVREYOLU/KAHRAMANMARAŞ ŞUBESİ",
    "1409": "YAKUPLU ŞUBESİ",
    "1420": "DİYARBAKIR SANAYİ",
    "1422": "BUYAKA ŞUBESİ",
    "1433": "BALÇOVA",
    "1442": "MAVİŞEHİR ŞUBESİ",
    "1503": "VESTEL CİTY BAĞLI",
    "90001": "IBAN MERKEZ ŞUBE",
    "90008": "EMKT MERKEZİ",
    "99999": "EFT MERKEZİ"
  }
}
